LICENSE
boxie/__init__.py
boxie/__main__.py
boxie/core.py
boxie/ui.py
boxie-1.3.1.dist-info/entry_points.txt
boxie-1.3.1.dist-info/LICENSE
boxie-1.3.1.dist-info/WHEEL
boxie-1.3.1.dist-info/METADATA
boxie-1.3.1.dist-info/RECORD
