Metadata-Version: 2.1
Name: boxie
Version: 1.3.1
Summary: Like Figlet but puts the text in a box
Home-page: https://github.com/UltiRequiem/boxie
Keywords: commands,utilities,cli
Author: Eliaz Bobadilla
Author-email: eliaz.bobadilladev@gmail.com
Requires-Python: >=3.7,<4.0
Classifier: Programming Language :: Python :: 3
Classifier: Programming Language :: Python :: 3.7
Classifier: Programming Language :: Python :: 3.8
Classifier: Programming Language :: Python :: 3.9
Requires-Dist: colorama (>=0.4.4,<0.5.0)
Project-URL: Repository, https://github.com/UltiRequiem/boxie
